py_context_llm7/__init__.py
py_context_llm7-0.1.0.dist-info/licenses/LICENSE
py_context_llm7-0.1.0.dist-info/METADATA
py_context_llm7-0.1.0.dist-info/WHEEL
py_context_llm7-0.1.0.dist-info/top_level.txt
py_context_llm7-0.1.0.dist-info/RECORD
