Metadata-Version: 2.4
Name: py-context-llm7
Version: 0.1.0
Summary: Minimal Python client for https://api.context.llm7.io
Home-page: https://github.com/chigwell/py-context-llm7
Author: Eugene Evstafev
Author-email: support@llm7.io
License: MIT
Project-URL: Source, https://github.com/chigwell/py-context-llm7
Project-URL: Issues, https://github.com/chigwell/py-context-llm7/issues
Keywords: llm,client,context,vector,rag
Classifier: License :: OSI Approved :: MIT License
Classifier: Development Status :: 3 - Alpha
Classifier: Intended Audience :: Developers
Classifier: Programming Language :: Python :: 3
Classifier: Programming Language :: Python :: 3 :: Only
Classifier: Programming Language :: Python :: 3.8
Classifier: Programming Language :: Python :: 3.9
Classifier: Programming Language :: Python :: 3.10
Classifier: Programming Language :: Python :: 3.11
Classifier: Programming Language :: Python :: 3.12
Classifier: Operating System :: OS Independent
Classifier: Topic :: Software Development :: Libraries :: Python Modules
Classifier: Topic :: Internet :: WWW/HTTP
Requires-Python: >=3.8
License-File: LICENSE
Requires-Dist: requests<3,>=2.28
Dynamic: author
Dynamic: author-email
Dynamic: classifier
Dynamic: description
Dynamic: description-content-type
Dynamic: home-page
Dynamic: keywords
Dynamic: license
Dynamic: license-file
Dynamic: project-url
Dynamic: requires-dist
Dynamic: requires-python
Dynamic: summary
